base64_utils/__init__.py
base64_utils/__init__.pyi
base64_utils/_base64_utils.pypy311-pp73-arm-linux-gnu.so
base64_utils/py.typed
base64_utils-0.2.0.dist-info/METADATA
base64_utils-0.2.0.dist-info/WHEEL
base64_utils-0.2.0.dist-info/RECORD
