Metadata-Version: 2.4
Name: base64_utils
Version: 0.2.0
Classifier: Programming Language :: Python
Classifier: Programming Language :: Python :: 3
Classifier: Programming Language :: Python :: 3 :: Only
Classifier: Programming Language :: Python :: 3.9
Classifier: Programming Language :: Python :: 3.10
Classifier: Programming Language :: Python :: 3.11
Classifier: Programming Language :: Python :: 3.12
Classifier: Programming Language :: Python :: 3.13
Classifier: Programming Language :: Python :: 3.14
Classifier: Programming Language :: Rust
Classifier: Programming Language :: Python :: Implementation :: CPython
Classifier: Programming Language :: Python :: Implementation :: PyPy
Summary: Fast, drop-in replacement for Python's base64 module, powered by Rust.
Author-email: Amin Alaee <mohammadamin.alaee@gmail.com>
Requires-Python: >=3.9
Project-URL: Documentation, https://github.com/aminalaee/base64_utils
Project-URL: Issues, https://github.com/aminalaee/base64_utils/issues
Project-URL: Source, https://github.com/aminalaee/base64_utils
